next_action/__init__.py
next_action/pick_action.py
next_action/arguments/__init__.py
next_action/arguments/config.py
next_action/arguments/parser.py
next_action/output/__init__.py
next_action/output/color.py
next_action/output/reference.py
next_action/output/url.py
next_action/output/warning.py
next_action/todotxt/__init__.py
next_action/todotxt/task.py
next_action/todotxt/tasks.py
tests/__init__.py
tests/create_random_todo_txt.py
tests/unittests/__init__.py
tests/unittests/fixtures.py
tests/unittests/test_cli.py
tests/unittests/test_pick_action.py
tests/unittests/arguments/__init__.py
tests/unittests/arguments/test_config.py
tests/unittests/arguments/test_parser.py
tests/unittests/output/__init__.py
tests/unittests/output/test_color.py
tests/unittests/output/test_reference.py
tests/unittests/output/test_render.py
tests/unittests/output/test_url.py
tests/unittests/output/test_warning.py
tests/unittests/todotxt/__init__.py
tests/unittests/todotxt/test_read_todotxt_files.py
tests/unittests/todotxt/test_task.py
tests/unittests/todotxt/test_tasks.py
next_action-1.13.0.dist-info/LICENSE
next_action-1.13.0.dist-info/METADATA
next_action-1.13.0.dist-info/WHEEL
next_action-1.13.0.dist-info/entry_points.txt
next_action-1.13.0.dist-info/top_level.txt
next_action-1.13.0.dist-info/zip-safe
next_action-1.13.0.dist-info/RECORD
