Metadata-Version: 2.1
Name: next-action
Version: 1.13.0
Summary: Command-line application to show the next action to work on from a todo.txt file
Home-page: https://github.com/fniessink/next-action
Author: Frank Niessink
Author-email: frank@niessink.com
License: Apache License, Version 2.0
Keywords: todo.txt,task management,todolist
Platform: UNKNOWN
Classifier: Development Status :: 5 - Production/Stable
Classifier: Environment :: Console
Classifier: Intended Audience :: End Users/Desktop
Classifier: License :: OSI Approved :: Apache Software License
Classifier: Natural Language :: English
Classifier: Operating System :: OS Independent
Classifier: Programming Language :: Python
Classifier: Programming Language :: Python :: 3.6
Classifier: Programming Language :: Python :: 3.7
Classifier: Programming Language :: Python :: 3.8
Classifier: Topic :: Office/Business :: Scheduling
Requires-Python: >=3.6
Requires-Dist: python-dateutil
Requires-Dist: Cerberus
Requires-Dist: PyYAML
Requires-Dist: Pygments
